rime/__init__.py
rime/basic/__init__.py
rime/basic/codes.py
rime/basic/commands.py
rime/basic/consts.py
rime/basic/test.py
rime/basic/targets/__init__.py
rime/basic/targets/problem.py
rime/basic/targets/project.py
rime/basic/targets/solution.py
rime/basic/targets/testset.py
rime/basic/util/__init__.py
rime/basic/util/test_summary.py
rime/core/__init__.py
rime/core/codes.py
rime/core/commands.py
rime/core/hooks.py
rime/core/main.py
rime/core/targets.py
rime/core/taskgraph.py
rime/core/ui.py
rime/plugins/__init__.py
rime/plugins/example.py
rime/plugins/htmlify_full.py
rime/plugins/markdownify_full.py
rime/plugins/merged_test.py
rime/plugins/rime_plus.py
rime/plugins/testlib_checker.py
rime/plugins/wikify.py
rime/plugins/wikify_full.py
rime/plugins/judge_system/__init__.py
rime/plugins/judge_system/aoj.py
rime/plugins/judge_system/atcoder.py
rime/plugins/judge_system/domjudge.py
rime/plugins/judge_system/hacker_rank.py
rime/plugins/plus/__init__.py
rime/plugins/plus/basic_patch.py
rime/plugins/plus/commands.py
rime/plugins/plus/flexible_judge.py
rime/plugins/plus/merged_test.py
rime/plugins/plus/subtask.py
rime/plugins/summary/__init__.py
rime/plugins/summary/html.ninja
rime/plugins/summary/md.ninja
rime/plugins/summary/pukiwiki.ninja
rime/plugins/summary/pukiwiki_full.ninja
rime/plugins/summary/summary.py
rime/util/__init__.py
rime/util/class_registry.py
rime/util/console.py
rime/util/files.py
rime/util/module_loader.py
rime/util/struct.py
rime-2.2.1.data/scripts/rime
rime-2.2.1.data/scripts/rime_init
rime-2.2.1.dist-info/LICENSE
rime-2.2.1.dist-info/METADATA
rime-2.2.1.dist-info/WHEEL
rime-2.2.1.dist-info/top_level.txt
rime-2.2.1.dist-info/RECORD
