Metadata-Version: 2.1
Name: rime
Version: 2.2.1
Summary: An automation tool for programming contest organizers
License-File: LICENSE
Requires-Dist: six
Requires-Dist: Jinja2
Requires-Dist: requests
